matatika/__init__.py
matatika/auth.py
matatika/catalog.py
matatika/channel.py
matatika/chartjs.py
matatika/context.py
matatika/dataset.py
matatika/exceptions.py
matatika/library.py
matatika/metadata.py
matatika/types.py
matatika/utility.py
matatika/cli/__init__.py
matatika/cli/display.py
matatika/cli/parse_service.py
matatika/cli/utility.py
matatika/cli/variables.py
matatika/cli/commands/__init__.py
matatika/cli/commands/context.py
matatika/cli/commands/delete.py
matatika/cli/commands/fetch.py
matatika/cli/commands/get.py
matatika/cli/commands/list_.py
matatika/cli/commands/profile.py
matatika/cli/commands/publish.py
matatika/cli/commands/root.py
tests/__init__.py
tests/api_response_mocks.py
tests/test_catalog.py
tests/test_channel.py
tests/test_chartjs_metadata.py
tests/test_dataset.py
tests/cli/__init__.py
tests/cli/test_cli.py
tests/cli/test_cli_delete.py
tests/cli/test_cli_fetch.py
tests/cli/test_cli_get.py
tests/cli/test_cli_list.py
tests/cli/test_cli_profile.py
tests/cli/test_cli_publish.py
tests/cli/test_variables.py
tests/cli/context/__init__.py
tests/cli/context/test_cli_context_create.py
tests/cli/context/test_cli_context_delete.py
tests/cli/context/test_cli_context_info.py
tests/cli/context/test_cli_context_list.py
tests/cli/context/test_cli_context_update.py
tests/cli/context/test_cli_context_use.py
tests/library/__init__.py
tests/library/test_library.py
tests/library/test_library_client.py
tests/library/test_library_delete_resources.py
tests/library/test_library_fetch.py
tests/library/test_library_list_resources.py
matatika-1.17.0.dist-info/LICENSE
matatika-1.17.0.dist-info/METADATA
matatika-1.17.0.dist-info/WHEEL
matatika-1.17.0.dist-info/entry_points.txt
matatika-1.17.0.dist-info/top_level.txt
matatika-1.17.0.dist-info/RECORD
