Metadata-Version: 2.1
Name: matatika
Version: 1.17.0
Summary: A Python utility for interfacing with the Matatika service
Home-page: https://www.matatika.com/
Author: Matatika
Author-email: support@matatika.com
License: Copyright (C) Matatika Limited - All Rights Reserved
Platform: UNKNOWN
Classifier: Development Status :: 4 - Beta
Classifier: Intended Audience :: Developers
Classifier: License :: Free To Use But Restricted
Classifier: Operating System :: OS Independent
Classifier: Programming Language :: Python :: 3
Classifier: Topic :: Software Development :: Libraries :: Python Modules
License-File: LICENSE
Requires-Dist: auth0-python (~=4.6.1)
Requires-Dist: click (~=8.1.7)
Requires-Dist: nbconvert (~=7.6.0)
Requires-Dist: python-dotenv (~=0.21.1)
Requires-Dist: pyyaml (~=6.0.1)
Requires-Dist: requests (~=2.31.0)
Provides-Extra: dev
Requires-Dist: autopep8 ; extra == 'dev'
Provides-Extra: lint
Requires-Dist: pylint ; extra == 'lint'
Provides-Extra: test
Requires-Dist: pytest ; extra == 'test'
Requires-Dist: requests-mock ; extra == 'test'
